MANIFEST.in
README.md
setup.cfg
setup.py
docs/HISTORY.txt
docs/INSTALL.txt
docs/LICENSE.GPL
docs/LICENSE.txt
seantis/__init__.py
seantis.dir.council.egg-info/PKG-INFO
seantis.dir.council.egg-info/SOURCES.txt
seantis.dir.council.egg-info/dependency_links.txt
seantis.dir.council.egg-info/entry_points.txt
seantis.dir.council.egg-info/namespace_packages.txt
seantis.dir.council.egg-info/not-zip-safe
seantis.dir.council.egg-info/requires.txt
seantis.dir.council.egg-info/top_level.txt
seantis/dir/__init__.py
seantis/dir/council/__init__.py
seantis/dir/council/configure.zcml
seantis/dir/council/directory.py
seantis/dir/council/item.py
seantis/dir/council/macros.py
seantis/dir/council/upgrades.py
seantis/dir/council/utils.py
seantis/dir/council/css/izug_basetheme.css
seantis/dir/council/css/izug_print.css
seantis/dir/council/locales/seantis.dir.council.pot
seantis/dir/council/locales/de/LC_MESSAGES/seantis.dir.council.mo
seantis/dir/council/locales/de/LC_MESSAGES/seantis.dir.council.po
seantis/dir/council/profiles/default/metadata.xml
seantis/dir/council/profiles/default/types.xml
seantis/dir/council/profiles/default/types/seantis.dir.council.directory.xml
seantis/dir/council/profiles/default/types/seantis.dir.council.item.xml
seantis/dir/council/profiles/izug_basetheme/cssregistry.xml
seantis/dir/council/templates/directory.pt
seantis/dir/council/templates/directorydetail.pt
seantis/dir/council/templates/item.pt
seantis/dir/council/templates/macros.pt