Metadata-Version: 1.1
Name: seantis.dir.council
Version: 1.5.1
Summary: Directory of Council Members
Home-page: https://github.com/seantis/seantis.dir.council
Author: Seantis GmbH
Author-email: info@seantis.ch
License: GPL
Keywords: council directory seantis plone dexterity
Platform: UNKNOWN
Classifier: Framework :: Plone
Classifier: Framework :: Plone :: 4.3
Classifier: Intended Audience :: Developers
Classifier: Topic :: Software Development :: Libraries :: Python Modules
Classifier: Programming Language :: Python
